droughtMoPro/__init__.py
droughtMoPro/data_manager.py
droughtMoPro/maps_pgdi.py
droughtMoPro/maps_sdi.py
droughtMoPro/reports.py
droughtMoPro/spatial_analysis.py
droughtMoPro/time_series.py
droughtMoPro-0.1.5.dist-info/LICENSE
droughtMoPro-0.1.5.dist-info/METADATA
droughtMoPro-0.1.5.dist-info/WHEEL
droughtMoPro-0.1.5.dist-info/top_level.txt
droughtMoPro-0.1.5.dist-info/RECORD
