Metadata-Version: 2.1
Name: droughtMoPro
Version: 0.1.5
Summary: Generator of drought monitoring products.
Home-page: https://github.com/rrealrangel/droughtMoPro
Author: R. A. Real-Rangel
Author-email: rrealr@iingen.unam.mx
License: GPL-3.0
Keywords: drought monitoring mapping series
Platform: UNKNOWN
Classifier: Development Status :: 4 - Beta
Classifier: Topic :: Scientific/Engineering :: Hydrology
Classifier: License :: OSI Approved :: GNU General Public License v3 (GPLv3)
Requires-Dist: datetime
Requires-Dist: dask
Requires-Dist: netcdf4
Requires-Dist: numpy
Requires-Dist: openpyxl
Requires-Dist: pandas
Requires-Dist: pathlib2
Requires-Dist: scipy
Requires-Dist: toml
Requires-Dist: toolz
Requires-Dist: xarray
